{
  "modelType": "Submodel",
  "id": "urn:aas:sm:CNC002:Nameplate",
  "idShort": "Nameplate",
  "semanticId": {
    "type": "ExternalReference",
    "keys": [
      {
        "type": "GlobalReference",
        "value": "0173-1#02-AAO677#002"
      }
    ]
  },
  "submodelElements": [
    {
      "modelType": "Property",
      "idShort": "ManufacturerName",
      "value": "HAAS",
      "valueType": "xs:string"
    },
    {
      "modelType": "Property",
      "idShort": "ProductDesignation",
      "value": "HAAS VF-2SS",
      "valueType": "xs:string"
    },
    {
      "modelType": "Property",
      "idShort": "SerialNumber",
      "value": "SN-CNC002",
      "valueType": "xs:string"
    }
  ]
}