{
  "modelType": "Submodel",
  "id": "urn:aas:sm:CNC002:OperationalData",
  "idShort": "OperationalData",
  "semanticId": {
    "type": "ExternalReference",
    "keys": [
      {
        "type": "GlobalReference",
        "value": "0173-1#02-AAV232#002"
      }
    ]
  },
  "submodelElements": [
    {
      "modelType": "Property",
      "idShort": "Status",
      "value": "RUNNING",
      "valueType": "xs:string",
      "timestamp": "2025-07-17T10:00:00"
    },
    {
      "modelType": "Property",
      "idShort": "HealthScore",
      "value": "90",
      "valueType": "xs:integer"
    },
    {
      "modelType": "Property",
      "idShort": "Temperature",
      "value": "25.3",
      "valueType": "xs:float",
      "unit": "°C"
    },
    {
      "modelType": "Property",
      "idShort": "CoolantFlow",
      "value": "10.8",
      "valueType": "xs:float",
      "unit": "L/min"
    },
    {
      "modelType": "Property",
      "idShort": "Pressure",
      "value": "5.2",
      "valueType": "xs:float",
      "unit": "bar"
    },
    {
      "modelType": "Property",
      "idShort": "Vibration",
      "value": "2.1",
      "valueType": "xs:float",
      "unit": "mm/s"
    }
  ]
}